<?xml version="1.0" encoding="ISO-8859-1"?>
<monitor-report>
	<parameters>
		<id>67</id>
		<organization>Beheerders</organization>
		<time-stamp>2009-04-02T15:11:51.277+02:00
		</time-stamp>
		<processing-time>837</processing-time>
		<date-start>2009-03-01</date-start>
		<date-end>2009-04-01</date-end>
	</parameters>
	<service name="WMS">
		<request-summary>
			<type-summary>
				<count>287</count>
				<type>REQUEST</type>
				<duration-avg>29351</duration-avg>
				<duration-max>2001544</duration-max>
				<data-size-sum>0</data-size-sum>
				<bytes-received-sum>66017</bytes-received-sum>
				<bytes-sent-sum>6118395</bytes-sent-sum>
			</type-summary>
		</request-summary>
		<response-frequency>
			<response-time>
				<duration-low>0</duration-low>
				<duration-high>1000</duration-high>
				<count>183</count>
				<type>CLIENT_TRANSFER</type>
			</response-time>
			<response-time>
				<duration-low>0</duration-low>
				<duration-high>1000</duration-high>
				<count>9</count>
				<type>COMBINE_IMAGES</type>
			</response-time>
			<response-time>
				<duration-low>0</duration-low>
				<duration-high>1000</duration-high>
				<count>156</count>
				<type>REQUEST</type>
			</response-time>
			<response-time>
				<duration-low>1000</duration-low>
				<duration-high>2000</duration-high>
				<count>21</count>
				<type>REQUEST</type>
			</response-time>
			<response-time>
				<duration-low>2000</duration-low>
				<duration-high>3000</duration-high>
				<count>8</count>
				<type>REQUEST</type>
			</response-time>
			<response-time>
				<duration-low>3000</duration-low>
				<duration-high>4000</duration-high>
				<count>13</count>
				<type>REQUEST</type>
			</response-time>
			<response-time>
				<duration-low>4000</duration-low>
				<duration-high>5000</duration-high>
				<count>11</count>
				<type>REQUEST</type>
			</response-time>
			<response-time>
				<duration-low>5000</duration-low>
				<duration-high>6000</duration-high>
				<count>6</count>
				<type>REQUEST</type>
			</response-time>
			<response-time>
				<duration-low>6000</duration-low>
				<duration-high>7000</duration-high>
				<count>4</count>
				<type>REQUEST</type>
			</response-time>
			<response-time>
				<duration-low>7000</duration-low>
				<duration-high>8000</duration-high>
				<count>6</count>
				<type>REQUEST</type>
			</response-time>
			<response-time>
				<duration-low>8000</duration-low>
				<duration-high>9000</duration-high>
				<count>2</count>
				<type>REQUEST</type>
			</response-time>
			<response-time>
				<duration-low>9000</duration-low>
				<duration-high>10000</duration-high>
				<count>2</count>
				<type>REQUEST</type>
			</response-time>
			<response-time>
				<duration-low>10000</duration-low>
				<duration-high>11000</duration-high>
				<count>2</count>
				<type>REQUEST</type>
			</response-time>
			<response-time>
				<duration-low>11000</duration-low>
				<duration-high>12000</duration-high>
				<count>1</count>
				<type>REQUEST</type>
			</response-time>
			<response-time>
				<duration-low>13000</duration-low>
				<duration-high>14000</duration-high>
				<count>1</count>
				<type>REQUEST</type>
			</response-time>
			<response-time>
				<duration-low>14000</duration-low>
				<duration-high>15000</duration-high>
				<count>1</count>
				<type>REQUEST</type>
			</response-time>
			<response-time>
				<duration-low>16000</duration-low>
				<duration-high>17000</duration-high>
				<count>1</count>
				<type>REQUEST</type>
			</response-time>
			<response-time>
				<duration-low>18000</duration-low>
				<duration-high>19000</duration-high>
				<count>2</count>
				<type>REQUEST</type>
			</response-time>
			<response-time>
				<duration-low>19000</duration-low>
				<duration-high>20000</duration-high>
				<count>1</count>
				<type>REQUEST</type>
			</response-time>
			<response-time>
				<duration-low>20000</duration-low>
				<duration-high>-1</duration-high>
				<count>49</count>
				<type>REQUEST</type>
			</response-time>
			<response-time>
				<duration-low>0</duration-low>
				<duration-high>1000</duration-high>
				<count>1</count>
				<type>SERVER_TRANSFER</type>
			</response-time>
			<response-time>
				<duration-low>1000</duration-low>
				<duration-high>2000</duration-high>
				<count>1</count>
				<type>SERVER_TRANSFER</type>
			</response-time>
			<response-time>
				<duration-low>2000</duration-low>
				<duration-high>3000</duration-high>
				<count>3</count>
				<type>SERVER_TRANSFER</type>
			</response-time>
			<response-time>
				<duration-low>3000</duration-low>
				<duration-high>4000</duration-high>
				<count>2</count>
				<type>SERVER_TRANSFER</type>
			</response-time>
			<response-time>
				<duration-low>4000</duration-low>
				<duration-high>5000</duration-high>
				<count>1</count>
				<type>SERVER_TRANSFER</type>
			</response-time>
			<response-time>
				<duration-low>7000</duration-low>
				<duration-high>8000</duration-high>
				<count>1</count>
				<type>SERVER_TRANSFER</type>
			</response-time>
		</response-frequency>
		<service-providers>
			<service-provider>
				<name>osm</name>
				<count>61</count>
				<duration-avg>1396</duration-avg>
				<duration-max>7957</duration-max>
				<bytes-received-sum>7024867</bytes-received-sum>
				<bytes-sent-sum>20361</bytes-sent-sum>
			</service-provider>
			<service-provider>
				<name>barb3p</name>
				<count>14</count>
				<duration-avg>582</duration-avg>
				<duration-max>915</duration-max>
				<bytes-received-sum>87773</bytes-received-sum>
				<bytes-sent-sum>4611</bytes-sent-sum>
			</service-provider>
		</service-providers>
		<request-load>
			<hourly-load>
				<date>2009-04-01</date>
				<hour>9</hour>
				<count>61</count>
				<duration-avg>1673</duration-avg>
				<duration-max>9253</duration-max>
				<bytes-received-sum>23119</bytes-received-sum>
				<bytes-sent-sum>5280208</bytes-sent-sum>
			</hourly-load>
			<hourly-load>
				<date>2009-03-24</date>
				<hour>10</hour>
				<count>2</count>
				<duration-avg>210</duration-avg>
				<duration-max>343</duration-max>
				<bytes-received-sum>190</bytes-received-sum>
				<bytes-sent-sum>5096</bytes-sent-sum>
			</hourly-load>
			<hourly-load>
				<date>2009-03-24</date>
				<hour>11</hour>
				<count>4</count>
				<duration-avg>846</duration-avg>
				<duration-max>1575</duration-max>
				<bytes-received-sum>824</bytes-received-sum>
				<bytes-sent-sum>33496</bytes-sent-sum>
			</hourly-load>
			<hourly-load>
				<date>2009-03-25</date>
				<hour>13</hour>
				<count>11</count>
				<duration-avg>1519</duration-avg>
				<duration-max>3534</duration-max>
				<bytes-received-sum>2123</bytes-received-sum>
				<bytes-sent-sum>675777</bytes-sent-sum>
			</hourly-load>
			<hourly-load>
				<date>2009-03-25</date>
				<hour>14</hour>
				<count>14</count>
				<duration-avg>70664</duration-avg>
				<duration-max>268388</duration-max>
				<bytes-received-sum>1330</bytes-received-sum>
				<bytes-sent-sum>4224</bytes-sent-sum>
			</hourly-load>
			<hourly-load>
				<date>2009-03-25</date>
				<hour>15</hour>
				<count>67</count>
				<duration-avg>1316</duration-avg>
				<duration-max>48163</duration-max>
				<bytes-received-sum>9730</bytes-received-sum>
				<bytes-sent-sum>19488</bytes-sent-sum>
			</hourly-load>
			<hourly-load>
				<date>2009-03-25</date>
				<hour>16</hour>
				<count>24</count>
				<duration-avg>374</duration-avg>
				<duration-max>1072</duration-max>
				<bytes-received-sum>9012</bytes-received-sum>
				<bytes-sent-sum>9698</bytes-sent-sum>
			</hourly-load>
			<hourly-load>
				<date>2009-03-25</date>
				<hour>17</hour>
				<count>3</count>
				<duration-avg>122252</duration-avg>
				<duration-max>295473</duration-max>
				<bytes-received-sum>1024</bytes-received-sum>
				<bytes-sent-sum>0</bytes-sent-sum>
			</hourly-load>
			<hourly-load>
				<date>2009-03-26</date>
				<hour>9</hour>
				<count>1</count>
				<duration-avg>1061</duration-avg>
				<duration-max>1061</duration-max>
				<bytes-received-sum>95</bytes-received-sum>
				<bytes-sent-sum>26929</bytes-sent-sum>
			</hourly-load>
			<hourly-load>
				<date>2009-03-26</date>
				<hour>10</hour>
				<count>19</count>
				<duration-avg>4287</duration-avg>
				<duration-max>64132</duration-max>
				<bytes-received-sum>4032</bytes-received-sum>
				<bytes-sent-sum>57748</bytes-sent-sum>
			</hourly-load>
			<hourly-load>
				<date>2009-03-26</date>
				<hour>11</hour>
				<count>2</count>
				<duration-avg>570</duration-avg>
				<duration-max>660</duration-max>
				<bytes-received-sum>452</bytes-received-sum>
				<bytes-sent-sum>0</bytes-sent-sum>
			</hourly-load>
			<hourly-load>
				<date>2009-03-26</date>
				<hour>12</hour>
				<count>4</count>
				<duration-avg>560605</duration-avg>
				<duration-max>2001544</duration-max>
				<bytes-received-sum>904</bytes-received-sum>
				<bytes-sent-sum>0</bytes-sent-sum>
			</hourly-load>
			<hourly-load>
				<date>2009-03-26</date>
				<hour>13</hour>
				<count>11</count>
				<duration-avg>110209</duration-avg>
				<duration-max>505839</duration-max>
				<bytes-received-sum>2177</bytes-received-sum>
				<bytes-sent-sum>969</bytes-sent-sum>
			</hourly-load>
			<hourly-load>
				<date>2009-03-26</date>
				<hour>14</hour>
				<count>7</count>
				<duration-avg>221150</duration-avg>
				<duration-max>625720</duration-max>
				<bytes-received-sum>1540</bytes-received-sum>
				<bytes-sent-sum>646</bytes-sent-sum>
			</hourly-load>
			<hourly-load>
				<date>2009-03-26</date>
				<hour>15</hour>
				<count>16</count>
				<duration-avg>52027</duration-avg>
				<duration-max>314241</duration-max>
				<bytes-received-sum>2311</bytes-received-sum>
				<bytes-sent-sum>2907</bytes-sent-sum>
			</hourly-load>
			<hourly-load>
				<date>2009-03-26</date>
				<hour>16</hour>
				<count>15</count>
				<duration-avg>17564</duration-avg>
				<duration-max>147110</duration-max>
				<bytes-received-sum>3573</bytes-received-sum>
				<bytes-sent-sum>1209</bytes-sent-sum>
			</hourly-load>
			<hourly-load>
				<date>2009-03-26</date>
				<hour>17</hour>
				<count>9</count>
				<duration-avg>14653</duration-avg>
				<duration-max>63876</duration-max>
				<bytes-received-sum>1422</bytes-received-sum>
				<bytes-sent-sum>0</bytes-sent-sum>
			</hourly-load>
			<hourly-load>
				<date>2009-03-30</date>
				<hour>8</hour>
				<count>4</count>
				<duration-avg>75670</duration-avg>
				<duration-max>119825</duration-max>
				<bytes-received-sum>508</bytes-received-sum>
				<bytes-sent-sum>0</bytes-sent-sum>
			</hourly-load>
			<hourly-load>
				<date>2009-03-30</date>
				<hour>9</hour>
				<count>12</count>
				<duration-avg>19114</duration-avg>
				<duration-max>80297</duration-max>
				<bytes-received-sum>1524</bytes-received-sum>
				<bytes-sent-sum>0</bytes-sent-sum>
			</hourly-load>
			<hourly-load>
				<date>2009-03-30</date>
				<hour>16</hour>
				<count>1</count>
				<duration-avg>1605</duration-avg>
				<duration-max>1605</duration-max>
				<bytes-received-sum>127</bytes-received-sum>
				<bytes-sent-sum>0</bytes-sent-sum>
			</hourly-load>
		</request-load>
	</service>
	<service name="WFS">
		<request-summary>
			<type-summary>
				<count>39</count>
				<type>REQUEST</type>
				<duration-avg>54957</duration-avg>
				<duration-max>728351</duration-max>
				<data-size-sum>0</data-size-sum>
				<bytes-received-sum>12228</bytes-received-sum>
				<bytes-sent-sum>6519</bytes-sent-sum>
			</type-summary>
		</request-summary>
		<response-frequency>
			<response-time>
				<duration-low>0</duration-low>
				<duration-high>1000</duration-high>
				<count>17</count>
				<type>CLIENT_TRANSFER</type>
			</response-time>
			<response-time>
				<duration-low>0</duration-low>
				<duration-high>1000</duration-high>
				<count>5</count>
				<type>REQUEST</type>
			</response-time>
			<response-time>
				<duration-low>1000</duration-low>
				<duration-high>2000</duration-high>
				<count>2</count>
				<type>REQUEST</type>
			</response-time>
			<response-time>
				<duration-low>2000</duration-low>
				<duration-high>3000</duration-high>
				<count>1</count>
				<type>REQUEST</type>
			</response-time>
			<response-time>
				<duration-low>3000</duration-low>
				<duration-high>4000</duration-high>
				<count>3</count>
				<type>REQUEST</type>
			</response-time>
			<response-time>
				<duration-low>4000</duration-low>
				<duration-high>5000</duration-high>
				<count>1</count>
				<type>REQUEST</type>
			</response-time>
			<response-time>
				<duration-low>5000</duration-low>
				<duration-high>6000</duration-high>
				<count>5</count>
				<type>REQUEST</type>
			</response-time>
			<response-time>
				<duration-low>7000</duration-low>
				<duration-high>8000</duration-high>
				<count>2</count>
				<type>REQUEST</type>
			</response-time>
			<response-time>
				<duration-low>9000</duration-low>
				<duration-high>10000</duration-high>
				<count>1</count>
				<type>REQUEST</type>
			</response-time>
			<response-time>
				<duration-low>10000</duration-low>
				<duration-high>11000</duration-high>
				<count>2</count>
				<type>REQUEST</type>
			</response-time>
			<response-time>
				<duration-low>14000</duration-low>
				<duration-high>15000</duration-high>
				<count>1</count>
				<type>REQUEST</type>
			</response-time>
			<response-time>
				<duration-low>15000</duration-low>
				<duration-high>16000</duration-high>
				<count>1</count>
				<type>REQUEST</type>
			</response-time>
			<response-time>
				<duration-low>20000</duration-low>
				<duration-high>-1</duration-high>
				<count>15</count>
				<type>REQUEST</type>
			</response-time>
		</response-frequency>
		<service-providers>
			<service-provider>
				<name>roopilot</name>
				<count>18</count>
				<duration-avg>14506</duration-avg>
				<duration-max>141153</duration-max>
				<bytes-received-sum>865092</bytes-received-sum>
				<bytes-sent-sum>6345</bytes-sent-sum>
			</service-provider>
			<service-provider>
				<name>rooprod</name>
				<count>12</count>
				<duration-avg>6049</duration-avg>
				<duration-max>24659</duration-max>
				<bytes-received-sum>142243</bytes-received-sum>
				<bytes-sent-sum>3060</bytes-sent-sum>
			</service-provider>
			<service-provider>
				<name>onbekend</name>
				<count>3</count>
				<duration-avg>282</duration-avg>
				<duration-max>449</duration-max>
				<bytes-received-sum>21150</bytes-received-sum>
				<bytes-sent-sum>719</bytes-sent-sum>
			</service-provider>
			<service-provider>
				<name>onbekend</name>
				<count>11</count>
				<duration-avg>2936</duration-avg>
				<duration-max>18276</duration-max>
				<bytes-received-sum>140401</bytes-received-sum>
				<bytes-sent-sum>2607</bytes-sent-sum>
			</service-provider>
		</service-providers>
		<request-load>
			<hourly-load>
				<date>2009-04-01</date>
				<hour>8</hour>
				<count>4</count>
				<duration-avg>4101</duration-avg>
				<duration-max>10853</duration-max>
				<bytes-received-sum>904</bytes-received-sum>
				<bytes-sent-sum>540</bytes-sent-sum>
			</hourly-load>
			<hourly-load>
				<date>2009-04-01</date>
				<hour>9</hour>
				<count>1</count>
				<duration-avg>1418</duration-avg>
				<duration-max>1418</duration-max>
				<bytes-received-sum>127</bytes-received-sum>
				<bytes-sent-sum>0</bytes-sent-sum>
			</hourly-load>
			<hourly-load>
				<date>2009-04-01</date>
				<hour>15</hour>
				<count>9</count>
				<duration-avg>116175</duration-avg>
				<duration-max>728351</duration-max>
				<bytes-received-sum>2892</bytes-received-sum>
				<bytes-sent-sum>1143</bytes-sent-sum>
			</hourly-load>
			<hourly-load>
				<date>2009-03-31</date>
				<hour>10</hour>
				<count>2</count>
				<duration-avg>9998</duration-avg>
				<duration-max>14616</duration-max>
				<bytes-received-sum>254</bytes-received-sum>
				<bytes-sent-sum>0</bytes-sent-sum>
			</hourly-load>
			<hourly-load>
				<date>2009-03-31</date>
				<hour>13</hour>
				<count>1</count>
				<duration-avg>23078</duration-avg>
				<duration-max>23078</duration-max>
				<bytes-received-sum>226</bytes-received-sum>
				<bytes-sent-sum>0</bytes-sent-sum>
			</hourly-load>
			<hourly-load>
				<date>2009-03-31</date>
				<hour>15</hour>
				<count>1</count>
				<duration-avg>154207</duration-avg>
				<duration-max>154207</duration-max>
				<bytes-received-sum>226</bytes-received-sum>
				<bytes-sent-sum>0</bytes-sent-sum>
			</hourly-load>
			<hourly-load>
				<date>2009-03-31</date>
				<hour>16</hour>
				<count>6</count>
				<duration-avg>22711</duration-avg>
				<duration-max>56960</duration-max>
				<bytes-received-sum>1890</bytes-received-sum>
				<bytes-sent-sum>1209</bytes-sent-sum>
			</hourly-load>
			<hourly-load>
				<date>2009-03-31</date>
				<hour>17</hour>
				<count>15</count>
				<duration-avg>49760</duration-avg>
				<duration-max>397877</duration-max>
				<bytes-received-sum>5709</bytes-received-sum>
				<bytes-sent-sum>3627</bytes-sent-sum>
			</hourly-load>
		</request-load>
	</service>
</monitor-report>